{
  "id":"6894d0f3-5848-4c5b-bbea-7c8106fbc8dc",
  "url":"scrum-why-we-do-what-we-do-part-3-solo",
  "author":"Mark Taylor",
  "published":"2014-08-17T21:35:00+01:00",
  "modified":"2014-08-18T17:21:26.961+01:00",
  "title":"Scrum - Why we do what we do - part 3, Solo development",
  "image":null,
  "description":"In this the third in my case study of why Scrum work for us, I solo development and the challenges to be overcome.",
  "enabled":true,
  "keyWords":["IT Management","Scrum", "Agile"],
  "redirects":[{"redirectType":301,"url":"http://blog.red-folder.com/2014/08/scrum-why-we-do-what-we-do-part-3-solo.html","redirectByRoute":false,"redirectByParameter":true}]
}
