{
  "id":"5e7a84e9-9991-4401-a926-f021ae959bbd",
  "url":"thoughts-on-my-time",
  "author":"Mark Taylor",
  "published":"2014-04-27T17:18:00.001+01:00",
  "modified":"2014-04-27T17:22:15.848+01:00",
  "title":"Thoughts on my time",
  "image":null,
  "description":"After quite a blogging gap, a catch up on what it happening in my world.",
  "enabled":true,
  "keyWords":["Visual Studio", "Extensions", "Cordova", "IT Management", "Bootstrap"],
  "redirects":[{"redirectType":301,"url":"http://blog.red-folder.com/2014/04/thoughts-on-my-time.html","redirectByRoute":false,"redirectByParameter":true}]
}
